cgminerhttpinterface/__init__.py
cgminerhttpinterface/command_line.py
cgminerhttpinterface/httprequesthandler.py
cgminerhttpinterface/rpcinterface.py
cgminerhttpinterface-0.1.3.dist-info/LICENSE
cgminerhttpinterface-0.1.3.dist-info/METADATA
cgminerhttpinterface-0.1.3.dist-info/WHEEL
cgminerhttpinterface-0.1.3.dist-info/entry_points.txt
cgminerhttpinterface-0.1.3.dist-info/top_level.txt
cgminerhttpinterface-0.1.3.dist-info/RECORD
