Metadata-Version: 2.1
Name: cgminerhttpinterface
Version: 0.1.3
Summary: HTTP endpoint for CGMiner RPC conforming interfaces
Home-page: http://github.com/rdugan/cgminerhttpinterface
Author: rdugan
Author-email: cgmhi-dev@mailnicks.org
License: Apache
Keywords: cgminer sgminer mining api http monitor
Platform: UNKNOWN
Classifier: Development Status :: 3 - Alpha
Classifier: Environment :: Web Environment
Classifier: Intended Audience :: End Users/Desktop
Classifier: Intended Audience :: Developers
Classifier: Intended Audience :: System Administrators
Classifier: License :: OSI Approved :: Apache Software License
Classifier: Programming Language :: Python :: 3.7
Classifier: Topic :: Internet :: WWW/HTTP :: HTTP Servers
Classifier: Topic :: Scientific/Engineering :: Interface Engine/Protocol Translator
Classifier: Topic :: System :: Networking :: Monitoring
Classifier: Topic :: System :: Systems Administration
Requires-Python: >=3
